abbyy_document_ai/__init__.py
abbyy_document_ai/_hooks/__init__.py
abbyy_document_ai/_hooks/registration.py
abbyy_document_ai/_hooks/sdkhooks.py
abbyy_document_ai/_hooks/types.py
abbyy_document_ai/_version.py
abbyy_document_ai/airwaybill_sdk.py
abbyy_document_ai/arrivalnotice_sdk.py
abbyy_document_ai/bankstatement_sdk.py
abbyy_document_ai/basesdk.py
abbyy_document_ai/basiccontract_sdk.py
abbyy_document_ai/billoflading_sdk.py
abbyy_document_ai/brokeragestatement_sdk.py
abbyy_document_ai/certificateoforigin_sdk.py
abbyy_document_ai/commercialinvoice_sdk.py
abbyy_document_ai/customsdeclaration_sdk.py
abbyy_document_ai/dangerousgoodsdeclaration_sdk.py
abbyy_document_ai/deliverynote_sdk.py
abbyy_document_ai/documentconversion.py
abbyy_document_ai/documents.py
abbyy_document_ai/hotelinvoice_sdk.py
abbyy_document_ai/httpclient.py
abbyy_document_ai/imagetotext.py
abbyy_document_ai/internationalconsignmentnote_sdk.py
abbyy_document_ai/invoice_sdk.py
abbyy_document_ai/models/__init__.py
abbyy_document_ai/models/airwaybill.py
abbyy_document_ai/models/airwaybillfields.py
abbyy_document_ai/models/apierror.py
abbyy_document_ai/models/arrivalnotice.py
abbyy_document_ai/models/arrivalnoticefields.py
abbyy_document_ai/models/badrequesterror.py
abbyy_document_ai/models/bankstatement.py
abbyy_document_ai/models/bankstatementfields.py
abbyy_document_ai/models/basiccontract.py
abbyy_document_ai/models/basiccontractfields.py
abbyy_document_ai/models/beginairwaybillfieldextractionop.py
abbyy_document_ai/models/beginairwaybillfieldextractionrequestbody.py
abbyy_document_ai/models/beginarrivalnoticefieldextractionop.py
abbyy_document_ai/models/beginarrivalnoticefieldextractionrequestbody.py
abbyy_document_ai/models/beginbankstatementfieldextractionop.py
abbyy_document_ai/models/beginbankstatementfieldextractionrequestbody.py
abbyy_document_ai/models/beginbasiccontractfieldextractionop.py
abbyy_document_ai/models/beginbasiccontractfieldextractionrequestbody.py
abbyy_document_ai-0.3.0.dist-info/METADATA
abbyy_document_ai-0.3.0.dist-info/WHEEL
abbyy_document_ai-0.3.0.dist-info/RECORD
